__init__.py
allure_pytest_auto/__init__.py
allure_pytest_auto/plugin.py
allure_pytest_auto/reporting/__init__.py
allure_pytest_auto/reporting/allure_manager.py
allure_pytest_auto/reporting/properties_writer.py
allure_pytest_auto/runner/__init__.py
allure_pytest_auto/runner/env.py
allure_pytest_auto/runner/execution_manager.py
allure_pytest_auto/settings/__init__.py
allure_pytest_auto/settings/config_loader.py
allure_pytest_auto-1.0.0.dist-info/licenses/LICENSE
allure_pytest_auto-1.0.0.dist-info/METADATA
allure_pytest_auto-1.0.0.dist-info/WHEEL
allure_pytest_auto-1.0.0.dist-info/entry_points.txt
allure_pytest_auto-1.0.0.dist-info/top_level.txt
allure_pytest_auto-1.0.0.dist-info/RECORD
