Metadata-Version: 2.4
Name: allure-pytest-auto
Version: 1.0.0
Summary: Pytest plugin generating timestamped Allure reports with configurable settings, CI/CD-ready. No more report overwrites.
License: MIT
Project-URL: Homepage, https://github.com/yourusername/allure-pytest-auto
Keywords: pytest,pytest-plugin,allure,allure-pytest,allure-pytest-auto,allure-report,selenium,test-reporting,automation-testing,qa-automation,ci-cd
Classifier: Framework :: Pytest
Classifier: Programming Language :: Python :: 3.8
Classifier: Programming Language :: Python :: 3.9
Classifier: Programming Language :: Python :: 3.10
Classifier: Programming Language :: Python :: 3.11
Classifier: Programming Language :: Python :: 3.12
Classifier: Programming Language :: Python :: 3.13
Classifier: License :: OSI Approved :: MIT License
Classifier: Topic :: Software Development :: Testing
Requires-Python: >=3.8
License-File: LICENSE
Requires-Dist: pytest>=7.0
Requires-Dist: allure-pytest>=2.13
Dynamic: license-file
